{
  "MD001": false,
  "MD013": false,
  "MD023": false,
  "MD024": false,
  "MD029": false,
  "MD033": {
    "allowed_elements": [
      "abbr",
      "Accordion",
      "Alert",
      "Check",
      "dd",
      "dl",
      "DNSProviderDocs",
      "Download",
      "DrushChangelog",
      "dt",
      "Enablement",
      "ExternalLink",
      "Icon",
      "LocaldevChangelog",
      "Partial",
      "Partial",
      "Popover",
      "ReviewDate",
      "Span",
      "Tab",
      "TabList",
      "Youtube"
    ]
  }
}
